communicationApp
