Metadata-Version: 2.1
Name: communicationAppModule
Version: 0.2.2
Summary: Module to connect with communication app and send message
Author: Wayne Shang
Author-email: wayne18308@gmail.com
License: MIT
Keywords: Communication App
Platform: UNKNOWN
License-File: LICENSE
